.gitignore
.pep8speaks.yml
.pyup.yml
.travis.yml
AUTHORS.md
CHANGELOG.md
CONTRIBUTING.md
LICENSE
MANIFEST.in
README.md
ROADMAP.md
appveyor.yml
asv.conf.json
build.cmd
pyproject.toml
requirements.txt
setup.py
tox.ini
benchmarks/__init__.py
benchmarks/benchmarks.py
examples/genotypes_count_alleles.ipynb
src/skallel_tensor/__init__.py
src/skallel_tensor/api.py
src/skallel_tensor/cuda_backend.py
src/skallel_tensor/dask_backend.py
src/skallel_tensor/numpy_backend.py
src/skallel_tensor/utils.py
src/skallel_tensor/version.py
src/skallel_tensor.egg-info/PKG-INFO
src/skallel_tensor.egg-info/SOURCES.txt
src/skallel_tensor.egg-info/dependency_links.txt
src/skallel_tensor.egg-info/not-zip-safe
src/skallel_tensor.egg-info/requires.txt
src/skallel_tensor.egg-info/top_level.txt
src/skallel_tensor/test/__init__.py
src/skallel_tensor/test/test_allele_counts.py
src/skallel_tensor/test/test_genotypes.py
src/skallel_tensor/test/test_selections.py
src/skallel_tensor/test/test_utils.py
src/skallel_tensor/test/test_variants_dataframe.py